{"version": 0.6, "generator": "Overpass API 0.7.62.8 e802775f", "osm3s": {"timestamp_osm_base": "2025-12-09T11:57:15Z", "copyright": "The data included in this document is from www.openstreetmap.org. The data is made available under ODbL."}, "elements": [{"type": "node", "id": 10742435523, "lat": 38.8851474, "lon": 37.6703744, "tags": {"addr:district": "Malatya", "amenity": "clinic", "check_date": "2023-02-07", "fixme": "resurvey after recovery", "healthcare": "clinic", "name": "Kuluncak Toplum Sagl\u0131g\u0131 Merkezi", "note": "\u0130stiklal Mah.", "phone": "+904226812010", "source": "SafeGraph"}}, {"type": "node", "id": 10742459481, "lat": 38.9539316, "lon": 37.8917934, "tags": {"addr:district": "Malatya", "amenity": "clinic", "check_date": "2023-02-07", "fixme": "resurvey after recovery", "healthcare": "clinic", "name": "Sagl\u0131k Ocag\u0131", "note": "H\u00fcrriyet Mah.", "phone": "+904227436518", "source": "SafeGraph"}}]}